montebarcode/__init__.py
montebarcode/checks.py
montebarcode/cli.py
montebarcode/codons.yml
montebarcode/generate.py
montebarcode/utils.py
monte_barcode-0.0.3.dist-info/LICENSE
monte_barcode-0.0.3.dist-info/METADATA
monte_barcode-0.0.3.dist-info/WHEEL
monte_barcode-0.0.3.dist-info/entry_points.txt
monte_barcode-0.0.3.dist-info/top_level.txt
monte_barcode-0.0.3.dist-info/RECORD
