Metadata-Version: 2.2
Name: monte-barcode
Version: 0.0.3
Summary: Generating sets of random DNA sequences optimized for use in high-throughput sequencing.
Author-email: Eachan Johnson <eachan.johnson@crick.ac.uk>
License: MIT License
Project-URL: Homepage, https://github.com/scbirlab/monte-barcode
Project-URL: Bug Tracker, https://github.com/scbirlab/monte-barcode/issues
Keywords: barcodes,sequencing,science,assay,biotechnology
Classifier: Development Status :: 3 - Alpha
Classifier: Intended Audience :: Science/Research
Classifier: Topic :: Scientific/Engineering :: Bio-Informatics
Classifier: License :: OSI Approved :: MIT License
Classifier: Programming Language :: Python :: 3.8
Classifier: Programming Language :: Python :: 3.9
Classifier: Programming Language :: Python :: 3.10
Classifier: Programming Language :: Python :: 3.11
Classifier: Programming Language :: Python :: 3.12
Classifier: Programming Language :: Python :: 3.13
Classifier: Programming Language :: Python :: 3 :: Only
Requires-Python: >=3.8
License-File: LICENSE
Requires-Dist: streq>=0.0.2
Requires-Dist: nemony>=0.0.2
Requires-Dist: tqdm
Requires-Dist: pyyaml
